berlin-1.0.0.dist-info/METADATA
berlin-1.0.0.dist-info/WHEEL
berlin-1.0.0.dist-info/license_files/LICENSE.md
berlin/__init__.py
berlin/_utils.py
berlin/_berlin.cpython-38-s390x-linux-gnu.so
berlin-1.0.0.dist-info/RECORD
