Metadata-Version: 2.1
Name: berlin
Version: 1.0.0
Classifier: Programming Language :: Rust
Classifier: Programming Language :: Python :: Implementation :: CPython
Classifier: Programming Language :: Python :: Implementation :: PyPy
License-File: LICENSE.md
Summary: Identify locations and tag them with UN-LOCODEs and ISO-3166-2 subdivisions.
Keywords: geospatial,nlp,search
Author-email: Metin Akat <metin.akat@flaxandteal.co.uk>, Phil Weir <phil.weir@flaxandteal.co.uk>
License: MIT
Requires-Python: >=3.8
Project-URL: Source Code, https://github.com/flaxandteal/berlin-py
